libggml/__init__.py
libggml/_version.py
libggml/include/ggml-alloc.h
libggml/include/ggml-backend.h
libggml/include/ggml-blas.h
libggml/include/ggml-cann.h
libggml/include/ggml-cpp.h
libggml/include/ggml-cpu.h
libggml/include/ggml-cuda.h
libggml/include/ggml-metal.h
libggml/include/ggml-opt.h
libggml/include/ggml-rpc.h
libggml/include/ggml-sycl.h
libggml/include/ggml-vulkan.h
libggml/include/ggml-webgpu.h
libggml/include/ggml-zendnn.h
libggml/include/ggml.h
libggml/include/gguf.h
libggml/lib64/libggml-base.so
libggml/lib64/libggml-base.so.0
libggml/lib64/libggml-base.so.0.9.5
libggml/lib64/libggml-cpu.so
libggml/lib64/libggml-cpu.so.0
libggml/lib64/libggml-cpu.so.0.9.5
libggml/lib64/libggml.so
libggml/lib64/libggml.so.0
libggml/lib64/libggml.so.0.9.5
libggml/lib64/cmake/ggml/ggml-config.cmake
libggml/lib64/cmake/ggml/ggml-version.cmake
libggml_python.libs/libgomp-a49a47f9.so.1.0.0
libggml_python-0.9.5.dist-info/METADATA
libggml_python-0.9.5.dist-info/WHEEL
libggml_python-0.9.5.dist-info/entry_points.txt
libggml_python-0.9.5.dist-info/RECORD
libggml_python-0.9.5.dist-info/licenses/LICENSE
libggml_python-0.9.5.dist-info/sboms/auditwheel.cdx.json
