Metadata-Version: 2.4
Name: libggml-python
Version: 0.9.5
Summary: Prebuilt ggml libraries
Author: benniekiss
License-Expression: MIT
Project-URL: Source, https://github.com/benniekiss/libggml-python
Project-URL: Tracker, https://github.com/benniekiss/libggml-python/issues
Project-URL: Upstream, https://github.com/ggml-org/ggml
Requires-Python: >=3.10
